fastaiv2/__init__.py
fastaiv2/_modidx.py
fastaiv2/_nbdev.py
fastaiv2/_pytorch_doc.py
fastaiv2/basics.py
fastaiv2/collab.py
fastaiv2/distributed.py
fastaiv2/fp16_utils.py
fastaiv2/imports.py
fastaiv2/interpret.py
fastaiv2/layers.py
fastaiv2/learner.py
fastaiv2/losses.py
fastaiv2/metrics.py
fastaiv2/optimizer.py
fastaiv2/patches.cp311-win_amd64.pyd
fastaiv2/test_utils.py
fastaiv2/torch_basics.py
fastaiv2/torch_core.py
fastaiv2/torch_imports.py
fastaiv2/callback/__init__.py
fastaiv2/callback/all.py
fastaiv2/callback/azureml.py
fastaiv2/callback/captum.py
fastaiv2/callback/channelslast.py
fastaiv2/callback/comet.py
fastaiv2/callback/core.py
fastaiv2/callback/data.py
fastaiv2/callback/fp16.py
fastaiv2/callback/hook.py
fastaiv2/callback/mixup.py
fastaiv2/callback/preds.py
fastaiv2/callback/progress.py
fastaiv2/callback/rnn.py
fastaiv2/callback/schedule.py
fastaiv2/callback/tensorboard.py
fastaiv2/callback/tracker.py
fastaiv2/callback/training.py
fastaiv2/callback/wandb.py
fastaiv2/data/__init__.py
fastaiv2/data/all.py
fastaiv2/data/block.py
fastaiv2/data/core.py
fastaiv2/data/download_checks.py
fastaiv2/data/external.py
fastaiv2/data/load.py
fastaiv2/data/transforms.py
fastaiv2/medical/__init__.py
fastaiv2/medical/imaging.py
fastaiv2/medical/text.py
fastaiv2/tabular/__init__.py
fastaiv2/tabular/all.py
fastaiv2/tabular/core.py
fastaiv2/tabular/data.py
fastaiv2/tabular/learner.py
fastaiv2/tabular/model.py
fastaiv2/text/__init__.py
fastaiv2/text/all.py
fastaiv2/text/core.py
fastaiv2/text/data.py
fastaiv2/text/learner.py
fastaiv2/text/models/__init__.py
fastaiv2/text/models/awdlstm.py
fastaiv2/text/models/core.py
fastaiv2/vision/__init__.py
fastaiv2/vision/all.py
fastaiv2/vision/augment.py
fastaiv2/vision/core.py
fastaiv2/vision/data.py
fastaiv2/vision/gan.py
fastaiv2/vision/learner.py
fastaiv2/vision/utils.py
fastaiv2/vision/widgets.py
fastaiv2/vision/models/__init__.py
fastaiv2/vision/models/all.py
fastaiv2/vision/models/tvm.py
fastaiv2/vision/models/unet.py
fastaiv2-1.0.6.dist-info/licenses/LICENSE
fastaiv2-1.0.6.dist-info/METADATA
fastaiv2-1.0.6.dist-info/WHEEL
fastaiv2-1.0.6.dist-info/entry_points.txt
fastaiv2-1.0.6.dist-info/top_level.txt
fastaiv2-1.0.6.dist-info/RECORD
